zy_log/__init__.py
zy_log/core.py
zy_log/loggers.py
zy_log/config/default_config.json
zy_log-0.1.2.dist-info/licenses/LICENSE
zy_log-0.1.2.dist-info/METADATA
zy_log-0.1.2.dist-info/WHEEL
zy_log-0.1.2.dist-info/top_level.txt
zy_log-0.1.2.dist-info/RECORD
