Metadata-Version: 2.4
Name: zy_log
Version: 0.1.2
Summary: An advanced, asynchronous logging system for algorithmic projects.
Author-email: zy <zhoumuci77@gamil.com>
License-Expression: MIT
Project-URL: Homepage, https://github.com/yaosterm/zy_log
Project-URL: Bug Tracker, https://github.com/yaosterm/zy_log/issues
Classifier: Programming Language :: Python :: 3
Classifier: Operating System :: OS Independent
Classifier: Topic :: System :: Logging
Requires-Python: >=3.8
License-File: LICENSE
Requires-Dist: rich>=13.0.0
Dynamic: license-file
